aily_code_sdk/__init__.py
aily_code_sdk/app.py
aily_code_sdk/conversation.py
aily_code_sdk/data.py
aily_code_sdk/integration/__init__.py
aily_code_sdk/integration/feishu.py
aily_code_sdk/knowledge.py
aily_code_sdk/llm.py
aily_code_sdk/skill.py
aily_code_sdk-0.1.0b8.dist-info/LICENSE
aily_code_sdk-0.1.0b8.dist-info/METADATA
aily_code_sdk-0.1.0b8.dist-info/WHEEL
aily_code_sdk-0.1.0b8.dist-info/RECORD
