Metadata-Version: 2.1
Name: aily-code-sdk
Version: 0.1.0b8
Summary: Aily Code SDK
Author: lijiuyang.5137
Author-email: lijiuyang.5137@bytedance.com
Requires-Python: >=3.8.1,<4.0.0
Classifier: License :: OSI Approved :: Apache Software License
Classifier: Programming Language :: Python :: 3
Classifier: Programming Language :: Python :: 3.9
Classifier: Programming Language :: Python :: 3.10
Classifier: Programming Language :: Python :: 3.11
Requires-Dist: aily-code-sdk-core (==0.1.0-beta.6)
Requires-Dist: openai (>=1.30.5,<2.0.0)
Requires-Dist: pydantic (>=2.7.2,<3.0.0)
